encoder/__init__.py
encoder/encoder.py
encoder/global_const_dir.py
encoder/main.py
hilla_encoder-0.0.6.dist-info/LICENSE
hilla_encoder-0.0.6.dist-info/METADATA
hilla_encoder-0.0.6.dist-info/WHEEL
hilla_encoder-0.0.6.dist-info/top_level.txt
hilla_encoder-0.0.6.dist-info/RECORD
