Metadata-Version: 2.1
Name: hilla-encoder
Version: 0.0.6
Summary: Encoder package
Home-page: https://gitlab.aws.pecan.ai/pecan/onboarding/hilla-pipeline
Author: Hilla Shahrabani
Author-email: hilla.s@pecan.ai
License: UNKNOWN
Platform: UNKNOWN
Classifier: Programming Language :: Python :: 3
Classifier: License :: OSI Approved :: MIT License
Classifier: Operating System :: OS Independent
Requires-Python: >=3.6
License-File: LICENSE
